decorators.py
django_api_decorators.py
django_api_decorators-0.0.3.dist-info/METADATA
django_api_decorators-0.0.3.dist-info/RECORD
django_api_decorators-0.0.3.dist-info/WHEEL
django_api_decorators-0.0.3.dist-info/top_level.txt
