Metadata-Version: 2.1
Name: django-api-decorators
Version: 0.0.3
Summary: Tiny decorator functions to make it easier to build an API using Django in ~100 LoC
Home-page: https://github.com/agilgur5/django-api-decorators
Author: Anton Gilgur
License: Apache-2.0
Project-URL: Source, https://github.com/agilgur5/django-api-decorators/
Project-URL: Tracker, https://github.com/agilgur5/django-api-decorators/issues
Keywords: django api rest ad-hoc decorator json dict form formset validation
Platform: UNKNOWN
Classifier: Natural Language :: English
Classifier: Intended Audience :: Developers
Classifier: Topic :: Software Development :: Libraries
Classifier: License :: OSI Approved :: Apache Software License
Classifier: Development Status :: 3 - Alpha
Classifier: Operating System :: OS Independent
Classifier: Programming Language :: Python :: 2
Classifier: Programming Language :: Python :: 2.7
Classifier: Programming Language :: Python :: 3
Classifier: Framework :: Django
Classifier: Framework :: Django :: 1.4
Classifier: Framework :: Django :: 1.5
Classifier: Framework :: Django :: 1.6
Classifier: Framework :: Django :: 1.7
Classifier: Framework :: Django :: 1.8
Classifier: Framework :: Django :: 1.9
Classifier: Framework :: Django :: 1.10
Classifier: Framework :: Django :: 1.11
Classifier: Framework :: Django :: 2.0
Classifier: Framework :: Django :: 2.1
Classifier: Framework :: Django :: 2.2
Requires-Python: >=2.7, <4
